kraken_infinity_grid/__init__.py
kraken_infinity_grid/_version.py
kraken_infinity_grid/cli.py
kraken_infinity_grid/database.py
kraken_infinity_grid/exceptions.py
kraken_infinity_grid/gridbot.py
kraken_infinity_grid/order_management.py
kraken_infinity_grid/setup.py
kraken_infinity_grid/state_machine.py
kraken_infinity_grid/telegram.py
kraken_infinity_grid-1.2.1.dist-info/licenses/LICENSE
kraken_infinity_grid-1.2.1.dist-info/METADATA
kraken_infinity_grid-1.2.1.dist-info/WHEEL
kraken_infinity_grid-1.2.1.dist-info/entry_points.txt
kraken_infinity_grid-1.2.1.dist-info/top_level.txt
kraken_infinity_grid-1.2.1.dist-info/RECORD
