Metadata-Version: 2.4
Name: kraken-infinity-grid
Version: 1.2.1
Summary: Infinity grid trading algorithm for the Kraken cryptocurrency exchange.
Author-email: Benjamin Thomas Schwertfeger <contact@b-schwertfeger.de>
Keywords: crypto,trading,kraken,exchange,api
Classifier: Development Status :: 5 - Production/Stable
Classifier: Environment :: Console
Classifier: Framework :: AsyncIO
Classifier: Framework :: Pytest
Classifier: Natural Language :: English
Classifier: Operating System :: MacOS
Classifier: Operating System :: Unix
Classifier: Programming Language :: Python :: 3.11
Classifier: Programming Language :: Python :: 3.12
Classifier: Programming Language :: Python :: 3.13
Classifier: Programming Language :: Python
Classifier: Topic :: Internet :: WWW/HTTP
Classifier: Topic :: Office/Business :: Financial :: Investment
Classifier: Topic :: Office/Business :: Financial
Classifier: Typing :: Typed
Requires-Python: >=3.11
License-File: LICENSE
Requires-Dist: asyncio~=3.4
Requires-Dist: click~=8.1
Requires-Dist: cloup~=3.0
Requires-Dist: python-kraken-sdk~=3.2
Requires-Dist: requests~=2.32
Requires-Dist: psycopg2-binary~=2.9
Requires-Dist: sqlalchemy~=2.0
Provides-Extra: dev
Requires-Dist: mypy; extra == "dev"
Requires-Dist: black; extra == "dev"
Requires-Dist: ruff; extra == "dev"
Provides-Extra: test
Requires-Dist: pytest; extra == "test"
Requires-Dist: pytest-cov; extra == "test"
Requires-Dist: pytest-asyncio; extra == "test"
Dynamic: license-file
